secure_transfer_protocol/__init__.py
secure_transfer_protocol/compression.py
secure_transfer_protocol/cryptographing.py
secure_transfer_protocol/logger.py
secure_transfer_protocol/time_sync.py
secure_transfer_protocol/transmission.py
secure_transfer_protocol-2.0.0.dist-info/licenses/LICENSE
secure_transfer_protocol-2.0.0.dist-info/METADATA
secure_transfer_protocol-2.0.0.dist-info/WHEEL
secure_transfer_protocol-2.0.0.dist-info/top_level.txt
secure_transfer_protocol-2.0.0.dist-info/RECORD
