Metadata-Version: 2.4
Name: secure_transfer_protocol
Version: 2.0.0
Summary: Secure Transfer Protocol with Post-Quantum Cryptography
Author-email: Konstantin Gorshkov <kostya_gorshkov_06@vk.com>
License: MIT
Project-URL: Repository, https://github.com/kostya2023/secure_transfer_protocol
Keywords: quantum,encryption,secure-transfer
Classifier: Programming Language :: Python :: 3
Classifier: Programming Language :: Rust
Classifier: Operating System :: POSIX :: Linux
Classifier: Operating System :: Microsoft :: Windows
Classifier: Topic :: Security :: Cryptography
Requires-Python: >=3.12
License-File: LICENSE
Requires-Dist: cffi>=1.17.1
Requires-Dist: colorama>=0.4.6
Requires-Dist: cryptography>=44.0.2
Requires-Dist: dilithium_python>=0.1.0
Requires-Dist: ntplib>=0.4.0
Requires-Dist: pycparser>=2.22
Requires-Dist: PythonKyber>=1.0.1
Dynamic: license-file
